twitteralert
