Metadata-Version: 2.1
Name: twitteralert
Version: 0.0.4
Summary: A package to alert from follower info in Twitter
Home-page: UNKNOWN
License: UNKNOWN
Platform: UNKNOWN
